pytomography/__init__.py
pytomography/algorithms/__init__.py
pytomography/algorithms/dip_recon.py
pytomography/algorithms/fbp.py
pytomography/algorithms/preconditioned_gradient_ascent.py
pytomography/callbacks/__init__.py
pytomography/callbacks/callback.py
pytomography/callbacks/data_saving.py
pytomography/data/collim.col
pytomography/data/ct_table.csv
pytomography/data/pet_colors.txt
pytomography/data/pet_scanner_info.txt
pytomography/data/siemens.erf
pytomography/data/simind.smc
pytomography/data/NIST_attenuation_data/adipose.csv
pytomography/data/NIST_attenuation_data/air.csv
pytomography/data/NIST_attenuation_data/aluminum.csv
pytomography/data/NIST_attenuation_data/bonecortical.csv
pytomography/data/NIST_attenuation_data/boneequivplastic.csv
pytomography/data/NIST_attenuation_data/breast.csv
pytomography/data/NIST_attenuation_data/lead.csv
pytomography/data/NIST_attenuation_data/lungtissue.csv
pytomography/data/NIST_attenuation_data/muscle.csv
pytomography/data/NIST_attenuation_data/tissueequivplastic.csv
pytomography/data/NIST_attenuation_data/tungsten.csv
pytomography/data/NIST_attenuation_data/water.csv
pytomography/io/__init__.py
pytomography/io/CT/__init__.py
pytomography/io/CT/dicom_ct_pd.py
pytomography/io/PET/__init__.py
pytomography/io/PET/clinical.py
pytomography/io/PET/gate.py
pytomography/io/PET/petsird.py
pytomography/io/PET/shared.py
pytomography/io/PET/prd/__init__.py
pytomography/io/PET/prd/_binary.py
pytomography/io/PET/prd/_dtypes.py
pytomography/io/PET/prd/_ndjson.py
pytomography/io/PET/prd/binary.py
pytomography/io/PET/prd/ndjson.py
pytomography/io/PET/prd/protocols.py
pytomography/io/PET/prd/types.py
pytomography/io/PET/prd/yardl_types.py
pytomography/io/SPECT/__init__.py
pytomography/io/SPECT/attenuation_map.py
pytomography/io/SPECT/dicom.py
pytomography/io/SPECT/shared.py
pytomography/io/SPECT/simind.py
pytomography/io/shared/__init__.py
pytomography/io/shared/dicom.py
pytomography/io/shared/dicom_creation.py
pytomography-3.4.0.dist-info/METADATA
pytomography-3.4.0.dist-info/WHEEL
pytomography-3.4.0.dist-info/licenses/LICENSE
pytomography-3.4.0.dist-info/RECORD
