Metadata-Version: 2.4
Name: pytomography
Version: 3.4.0
Summary: Package to perform tomographic image reconstruction
Project-URL: Homepage, https://github.com/qurit/PyTomography
Project-URL: Bug Tracker, https://github.com/qurit/PyTomography/issues
Author-email: Luke Polson <lukepolson@outlook.com>
License-File: LICENSE
Classifier: License :: OSI Approved :: MIT License
Classifier: Operating System :: OS Independent
Classifier: Programming Language :: Python :: 3
Requires-Python: >=3.9
Requires-Dist: fft-conv-pytorch>=1.2.0
Requires-Dist: h5py>=3.11.0
Requires-Dist: kornia>=0.6.12
Requires-Dist: matplotlib>=3.8.0
Requires-Dist: nibabel>=5.1.0
Requires-Dist: numpy>=1.24.2
Requires-Dist: pandas>=2.2
Requires-Dist: pydicom>=3.0.1
Requires-Dist: rt-utils>=1.2.0
Requires-Dist: scipy>=1.10.1
Requires-Dist: torch>=1.10.2
Requires-Dist: torchrbf
Requires-Dist: uproot>=5.2.1
Provides-Extra: doc
Requires-Dist: furo; extra == 'doc'
Requires-Dist: ipykernel; extra == 'doc'
Requires-Dist: myst-parser; extra == 'doc'
Requires-Dist: nbsphinx; extra == 'doc'
Requires-Dist: pydata-sphinx-theme; extra == 'doc'
Requires-Dist: sphinx-autoapi~=3.0.0; extra == 'doc'
Requires-Dist: sphinx-copybutton; extra == 'doc'
Requires-Dist: sphinx-design; extra == 'doc'
Requires-Dist: sphinx~=6.2.1; extra == 'doc'
Requires-Dist: toml; extra == 'doc'
